{"doi":"10.1111\/1468-5965.t01-1-00416","coreId":"212092","oai":"oai:eprints.lse.ac.uk:24161","identifiers":["oai:eprints.lse.ac.uk:24161","10.1111\/1468-5965.t01-1-00416"],"title":"Book review: questioning sovereignty: law, state, and nation in the European commonwealth, by N. MacCormick","authors":["Murkens, Jo Eric"],"enrichments":{"references":[],"documentType":{"type":null}},"contributors":[],"datePublished":"2003-03","abstract":null,"downloadUrl":"","fullTextIdentifier":null,"pdfHashValue":null,"publisher":"Wiley-Blackwell Publishing in association with UACES, the University Association for Contemporary European Studies","rawRecordXml":"<record><header><identifier>\n    \n    \n      oai:eprints.lse.ac.uk:24161<\/identifier><datestamp>\n      2017-01-04T16:14:00Z<\/datestamp><setSpec>\n      74797065733D4445505453:4C53452D4C4C<\/setSpec><\/header><metadata><oai_dc:dc xmlns:oai_dc=\"http:\/\/www.openarchives.org\/OAI\/2.0\/oai_dc\/\" xmlns:dc=\"http:\/\/purl.org\/dc\/elements\/1.1\/\" xmlns:xsi=\"http:\/\/www.w3.org\/2001\/XMLSchema-instance\" xsi:schemaLocation=\"http:\/\/www.openarchives.org\/OAI\/2.0\/oai_dc\/ http:\/\/www.openarchives.org\/OAI\/2.0\/oai_dc.xsd\" ><dc:relation>\n    \n      \n        http:\/\/eprints.lse.ac.uk\/24161\/<\/dc:relation><dc:title>\n        Book review: questioning sovereignty: law, state, and nation in the European commonwealth, by N. MacCormick<\/dc:title><dc:creator>\n        Murkens, Jo Eric<\/dc:creator><dc:subject>\n        D901 Europe (General)<\/dc:subject><dc:subject>\n        K Law (General)<\/dc:subject><dc:publisher>\n        Wiley-Blackwell Publishing in association with UACES, the University Association for Contemporary European Studies<\/dc:publisher><dc:date>\n        2003-03<\/dc:date><dc:type>\n        Article<\/dc:type><dc:type>\n        NonPeerReviewed<\/dc:type><dc:identifier>\n          Murkens, Jo Eric  (2003) Book review: questioning sovereignty: law, state, and nation in the European commonwealth, by N. MacCormick.  Journal of Common Market Studies, 41 (1).  p. 171.  ISSN 1468-5965     <\/dc:identifier><dc:relation>\n        http:\/\/www.wiley.com\/bw\/journal.asp?ref=0021-9886<\/dc:relation><dc:relation>\n        10.1111\/1468-5965.t01-1-00416<\/dc:relation><\/oai_dc:dc><\/metadata><\/record>","journals":null,"language":null,"relations":["http:\/\/eprints.lse.ac.uk\/24161\/","http:\/\/www.wiley.com\/bw\/journal.asp?ref=0021-9886","10.1111\/1468-5965.t01-1-00416"],"year":2003,"topics":["D901 Europe (General)","K Law (General)"],"subject":["Article","NonPeerReviewed"],"fullText":null}