{"doi":"10.1080\/01972240490481009","coreId":"206713","oai":"oai:eprints.lse.ac.uk:15518","identifiers":["oai:eprints.lse.ac.uk:15518","10.1080\/01972240490481009"],"title":"On the margins of the \"information society\": a comparative study of mediation","authors":["Beck, Eevi","Madon, Shirin","Sahay, Sundeep"],"enrichments":{"references":[],"documentType":{"type":null}},"contributors":[],"datePublished":"2004-09","abstract":null,"downloadUrl":"","fullTextIdentifier":null,"pdfHashValue":null,"publisher":"Taylor & Francis","rawRecordXml":"<record><header><identifier>\n    \n    \n      oai:eprints.lse.ac.uk:15518<\/identifier><datestamp>\n      2017-10-31T12:20:28Z<\/datestamp><setSpec>\n      74797065733D43454E54524553:4C53455F52435F496E666F5F537973<\/setSpec><setSpec>\n      74797065733D4445505453:4C53452D4D414E<\/setSpec><\/header><metadata><oai_dc:dc xmlns:oai_dc=\"http:\/\/www.openarchives.org\/OAI\/2.0\/oai_dc\/\" xmlns:dc=\"http:\/\/purl.org\/dc\/elements\/1.1\/\" xmlns:xsi=\"http:\/\/www.w3.org\/2001\/XMLSchema-instance\" xsi:schemaLocation=\"http:\/\/www.openarchives.org\/OAI\/2.0\/oai_dc\/ http:\/\/www.openarchives.org\/OAI\/2.0\/oai_dc.xsd\" ><dc:relation>\n    \n      \n        http:\/\/eprints.lse.ac.uk\/15518\/<\/dc:relation><dc:title>\n        On the margins of the \"information society\": a comparative study of mediation<\/dc:title><dc:creator>\n        Beck, Eevi<\/dc:creator><dc:creator>\n        Madon, Shirin<\/dc:creator><dc:creator>\n        Sahay, Sundeep<\/dc:creator><dc:subject>\n        H Social Sciences (General)<\/dc:subject><dc:publisher>\n        Taylor & Francis<\/dc:publisher><dc:date>\n        2004-09<\/dc:date><dc:type>\n        Article<\/dc:type><dc:type>\n        PeerReviewed<\/dc:type><dc:identifier>\n          Beck, Eevi and Madon, Shirin and Sahay, Sundeep  (2004) On the margins of the \"information society\": a comparative study of mediation.  Information Society, 20 (4).  pp. 279-290.  ISSN 0197-2243     <\/dc:identifier><dc:relation>\n        http:\/\/www.informaworld.com\/0197-2243<\/dc:relation><dc:relation>\n        10.1080\/01972240490481009<\/dc:relation><\/oai_dc:dc><\/metadata><\/record>","journals":null,"language":null,"relations":["http:\/\/eprints.lse.ac.uk\/15518\/","http:\/\/www.informaworld.com\/0197-2243","10.1080\/01972240490481009"],"year":2004,"topics":["H Social Sciences (General)"],"subject":["Article","PeerReviewed"],"fullText":null}